ROSSO/__init__.py
ROSSO/cli.py
ROSSO-0.1.0.dist-info/METADATA
ROSSO-0.1.0.dist-info/WHEEL
ROSSO-0.1.0.dist-info/entry_points.txt
ROSSO-0.1.0.dist-info/top_level.txt
ROSSO-0.1.0.dist-info/RECORD
