Metadata-Version: 2.2
Name: ROSSO
Version: 0.1.0
Summary: A simple Hello World package
Home-page: https://github.com/yourusername/hello_world
Author: Gabriele Gabrielli
Author-email: your.email@example.com
Classifier: Programming Language :: Python :: 3
Classifier: License :: OSI Approved :: MIT License
Classifier: Operating System :: OS Independent
Requires-Python: >=3.7
Requires-Dist: click>=7.0
